torchnmf/__init__.py
torchnmf/constants.py
torchnmf/metrics.py
torchnmf/nmf.py
torchnmf/plca.py
torchnmf/trainer.py
torchnmf/utils.py
torchnmf-0.3.5.dist-info/LICENSE
torchnmf-0.3.5.dist-info/METADATA
torchnmf-0.3.5.dist-info/WHEEL
torchnmf-0.3.5.dist-info/top_level.txt
torchnmf-0.3.5.dist-info/RECORD
