Metadata-Version: 2.1
Name: torchnmf
Version: 0.3.5
Summary: A pytorch package for Non-negative Matrix Factorization
Home-page: https://github.com/yoyololicon/pytorch-NMF
Author: Chin-Yun Yu
Author-email: lolimaster.cs03@nctu.edu.tw
Classifier: Programming Language :: Python :: 3
Classifier: License :: OSI Approved :: MIT License
Classifier: Operating System :: OS Independent
License-File: LICENSE
Requires-Dist: torch (>=1.4)
Requires-Dist: tqdm
